{
  "nodes": [
      {
    "id": "start",
    "text": "Bienvenue sur cette histoire d'example",
    "end": "not",
    "minutes_to_wait": "0",
    "is_user": "false",
    "conditional_activation": {
      "activated_by_key": "",
      "activated_by_value": "",
      "activate_key": "",
      "activate_value": ""
    }
  }
,  {
    "id": "2f1e0b7b-5dda-4b5f-a3ee-a744563eb9af",
    "text": "Nous essayons ici les différentes fonctionnalités. Vers quelle fin veux-tu aller ?",
    "end": "not",
    "minutes_to_wait": "0",
    "is_user": "false",
    "conditional_activation": {
      "activated_by_key": "",
      "activated_by_value": "",
      "activate_key": "",
      "activate_value": ""
    }
  }
,  {
    "id": "659ce6ef-e818-4301-8c6f-87cb66795ae3",
    "text": "la fin heureuse",
    "end": "not",
    "minutes_to_wait": "0",
    "is_user": "true",
    "conditional_activation": {
      "activated_by_key": "",
      "activated_by_value": "",
      "activate_key": "",
      "activate_value": ""
    }
  }
,  {
    "id": "4b143c9b-1d29-45ac-95a9-058b63982dab",
    "text": "la fin malheureuse",
    "end": "not",
    "minutes_to_wait": "0",
    "is_user": "true",
    "conditional_activation": {
      "activated_by_key": "",
      "activated_by_value": "",
      "activate_key": "",
      "activate_value": ""
    }
  }
,  {
    "id": "73696f50-4db7-457c-9c4f-bdcf60261e84",
    "text": "perdu",
    "end": "bad",
    "minutes_to_wait": "0",
    "is_user": "false",
    "conditional_activation": {
      "activated_by_key": "",
      "activated_by_value": "",
      "activate_key": "",
      "activate_value": ""
    }
  }
,  {
    "id": "977edcef-2589-4ce3-8303-af2020b60996",
    "text": "un dialogue avec un délai",
    "end": "not",
    "minutes_to_wait": "0",
    "is_user": "true",
    "conditional_activation": {
      "activated_by_key": "",
      "activated_by_value": "",
      "activate_key": "",
      "activate_value": ""
    }
  }
,  {
    "id": "e37c9b1e-3c25-4731-83a1-f58a438f4f39",
    "text": "gagné",
    "end": "good",
    "minutes_to_wait": "0",
    "is_user": "false",
    "conditional_activation": {
      "activated_by_key": "",
      "activated_by_value": "",
      "activate_key": "",
      "activate_value": ""
    }
  }
,  {
    "id": "7632ad5e-e7b4-44ef-bc36-74f7770ddc0b",
    "text": "très bien, tu devrais voir ça après 10 minutes (du jeu)",
    "end": "not",
    "minutes_to_wait": "10",
    "is_user": "false",
    "conditional_activation": {
      "activated_by_key": "",
      "activated_by_value": "",
      "activate_key": "",
      "activate_value": ""
    }
  }
,  {
    "id": "f009a6f9-421b-4fa4-9a4c-781d78463ba5",
    "text": "et ça après 20 minutes",
    "end": "not",
    "minutes_to_wait": "20",
    "is_user": "false",
    "conditional_activation": {
      "activated_by_key": "",
      "activated_by_value": "",
      "activate_key": "",
      "activate_value": ""
    }
  }
,  {
    "id": "dd46e6a3-2908-4a5b-990c-81b6f89c9152",
    "text": "test",
    "end": "not",
    "minutes_to_wait": "0",
    "is_user": "false",
    "conditional_activation": {
      "activated_by_key": "test",
      "activated_by_value": "test",
      "activate_key": "",
      "activate_value": ""
    }
  }

  ],
  "edges": [
      {
    "from": "start",
    "to": "2f1e0b7b-5dda-4b5f-a3ee-a744563eb9af"
  }
,  {
    "from": "2f1e0b7b-5dda-4b5f-a3ee-a744563eb9af",
    "to": "659ce6ef-e818-4301-8c6f-87cb66795ae3"
  }
,  {
    "from": "2f1e0b7b-5dda-4b5f-a3ee-a744563eb9af",
    "to": "4b143c9b-1d29-45ac-95a9-058b63982dab"
  }
,  {
    "from": "4b143c9b-1d29-45ac-95a9-058b63982dab",
    "to": "73696f50-4db7-457c-9c4f-bdcf60261e84"
  }
,  {
    "from": "2f1e0b7b-5dda-4b5f-a3ee-a744563eb9af",
    "to": "977edcef-2589-4ce3-8303-af2020b60996"
  }
,  {
    "from": "659ce6ef-e818-4301-8c6f-87cb66795ae3",
    "to": "e37c9b1e-3c25-4731-83a1-f58a438f4f39"
  }
,  {
    "from": "977edcef-2589-4ce3-8303-af2020b60996",
    "to": "7632ad5e-e7b4-44ef-bc36-74f7770ddc0b"
  }
,  {
    "from": "7632ad5e-e7b4-44ef-bc36-74f7770ddc0b",
    "to": "f009a6f9-421b-4fa4-9a4c-781d78463ba5"
  }
,  {
    "from": "f009a6f9-421b-4fa4-9a4c-781d78463ba5",
    "to": "dd46e6a3-2908-4a5b-990c-81b6f89c9152"
  }

  ]
}
